icecap/__init__.py
icecap/constants.py
icecap/agent/v1/__init__.py
icecap/agent/v1/commands_pb2.py
icecap/agent/v1/commands_pb2.pyi
icecap/agent/v1/common_pb2.py
icecap/agent/v1/common_pb2.pyi
icecap/agent/v1/events_pb2.py
icecap/agent/v1/events_pb2.pyi
icecap/data/mapping/gameobject_template.csv
icecap/domain/__init__.py
icecap/domain/dto/__init__.py
icecap/domain/dto/game_object_fields.py
icecap/domain/dto/position.py
icecap/domain/dto/unit_fields.py
icecap/domain/enums/__init__.py
icecap/domain/enums/entity_type.py
icecap/domain/enums/faction.py
icecap/domain/enums/gender.py
icecap/domain/enums/player_class.py
icecap/domain/enums/race.py
icecap/domain/models/__init__.py
icecap/domain/models/entity.py
icecap/domain/models/game_objects.py
icecap/domain/models/player.py
icecap/domain/models/unit.py
icecap/infrastructure/__init__.py
icecap/infrastructure/communication/__init__.py
icecap/infrastructure/communication/rpc/__init__.py
icecap/infrastructure/communication/rpc/exceptions.py
icecap/infrastructure/communication/rpc/factory.py
icecap/infrastructure/communication/rpc/interface.py
icecap/infrastructure/communication/rpc/tcp/__init__.py
icecap/infrastructure/communication/rpc/tcp/client.py
icecap/infrastructure/communication/rpc/tcp/connection.py
icecap/infrastructure/communication/rpc/tcp/dispatcher.py
icecap/infrastructure/communication/rpc/tcp/protocol.py
icecap/infrastructure/driver/__init__.py
icecap/infrastructure/driver/driver.py
icecap/infrastructure/driver/object_manager.py
icecap/infrastructure/driver/offsets.py
icecap/infrastructure/driver/ctypes/__init__.py
icecap/infrastructure/driver/ctypes/base.py
icecap/infrastructure/driver/ctypes/game_object_fields.py
icecap/infrastructure/driver/ctypes/object_position.py
icecap/infrastructure/driver/ctypes/unit_fields.py
icecap/infrastructure/memory_manager/__init__.py
icecap/infrastructure/memory_manager/factory.py
icecap/infrastructure/memory_manager/interface.py
icecap/infrastructure/memory_manager/linux.py
icecap-0.7.0.dist-info/licenses/LICENSE
icecap-0.7.0.dist-info/METADATA
icecap-0.7.0.dist-info/WHEEL
icecap-0.7.0.dist-info/top_level.txt
icecap-0.7.0.dist-info/RECORD
