Metadata-Version: 2.4
Name: icecap
Version: 0.7.0
Summary: A Python library for building World of Warcraft assistant applications
Author-email: Eugene Prodan <mora9715@gmail.com>
License: MIT License
Project-URL: Homepage, https://github.com/mora9715/icecap
Project-URL: Bug Tracker, https://github.com/mora9715/icecap/issues
Classifier: Programming Language :: Python :: 3
Classifier: License :: OSI Approved :: MIT License
Classifier: Operating System :: OS Independent
Classifier: Development Status :: 3 - Alpha
Requires-Python: >=3.10
License-File: LICENSE
Requires-Dist: psutil
Requires-Dist: pymem; platform_system == "Windows"
Requires-Dist: protobuf
Provides-Extra: navigation
Requires-Dist: pillow; extra == "navigation"
Dynamic: license-file
